LICENSE
MANIFEST.in
README.md
README.zh-CN.md
requirements.txt
setup.py
keras_ordered_neurons/__init__.py
keras_ordered_neurons/activations.py
keras_ordered_neurons/layers.py
keras_ordered_neurons.egg-info/PKG-INFO
keras_ordered_neurons.egg-info/SOURCES.txt
keras_ordered_neurons.egg-info/dependency_links.txt
keras_ordered_neurons.egg-info/top_level.txt
tests/__init__.py
tests/test_activations.py
tests/test_layers.py