Metadata-Version: 2.1
Name: keras-ordered-neurons
Version: 0.10.0
Summary: Unofficial implementation of ON-LSTM
Home-page: https://github.com/CyberZHG/keras-ordered-neurons
Author: CyberZHG
Author-email: CyberZHG@users.noreply.github.com
License: Anti 996
Platform: UNKNOWN
Classifier: Programming Language :: Python :: 3
Classifier: License :: OSI Approved :: MIT License
Classifier: Operating System :: OS Independent
